wintop/__init__.py
wintop/wintop.py
wintop-1.0.1.dist-info/licenses/LICENSE
wintop-1.0.1.dist-info/METADATA
wintop-1.0.1.dist-info/WHEEL
wintop-1.0.1.dist-info/entry_points.txt
wintop-1.0.1.dist-info/top_level.txt
wintop-1.0.1.dist-info/RECORD
